murpheus/__init__.py
murpheus/batch_processing.py
murpheus/data_loading.py
murpheus/filters.py
murphy/__init__.py
murphy/batch_processing.py
murphy/data_loading.py
murphy/filters.py
smpamorpheus/__init__.py
smpamorpheus/batch_processing.py
smpamorpheus/data_loading.py
smpamorpheus/filters.py
murpheus-0.6.dist-info/LICENSE.txt
murpheus-0.6.dist-info/METADATA
murpheus-0.6.dist-info/WHEEL
murpheus-0.6.dist-info/top_level.txt
murpheus-0.6.dist-info/RECORD
