Metadata-Version: 2.1
Name: murpheus
Version: 0.6
Summary: Murpheus is a powerful processor that is used to analyze a ton of twitter data from the internet archive.
Home-page: https://github.com/Social-Media-Public-Analysis/murpheus
Author: Ali Abbas
Author-email: v2thegreat@gmail.com
License: MIT
Download-URL: https://github.com/Social-Media-Public-Analysis/murpheus/archive/v_06.tar.gz
Keywords: DASK,BIG DATA,MACHINE LEARNING
Platform: UNKNOWN
Classifier: Development Status :: 3 - Alpha
Classifier: Intended Audience :: Developers
Classifier: Topic :: Software Development :: Build Tools
Classifier: License :: OSI Approved :: MIT License
Classifier: Programming Language :: Python :: 3.6
Requires-Dist: tqdm
Requires-Dist: numpy
Requires-Dist: pandas
Requires-Dist: dask[complete]
Requires-Dist: nltk
Requires-Dist: pytest
Requires-Dist: pyfiglet
